potentialflowvisualizer/__init__.py
potentialflowvisualizer/flowfield.py
potentialflowvisualizer/objects.py
PotentialFlowVisualizer-0.2.1.dist-info/METADATA
PotentialFlowVisualizer-0.2.1.dist-info/WHEEL
PotentialFlowVisualizer-0.2.1.dist-info/top_level.txt
PotentialFlowVisualizer-0.2.1.dist-info/RECORD
