Metadata-Version: 2.1
Name: PotentialFlowVisualizer
Version: 0.2.1
Summary: A fun, lightweight tool to visualize potential flows quickly!
Home-page: https://peterdsharpe.github.io/PotentialFlowVisualizer/
Author: Peter Sharpe
Author-email: peterdsharpe@gmail.com
License: UNKNOWN
Project-URL: Bug Reports, https://github.com/peterdsharpe/PotentialFlowVisualizer/issues
Project-URL: Source, https://github.com/peterdsharpe/PotentialFlowVisualizer
Keywords: potential flow aerodynamics hydrodynamics air fluid dynamics mechanics
Platform: UNKNOWN
Classifier: Development Status :: 4 - Beta
Classifier: Intended Audience :: Science/Research
Classifier: Topic :: Scientific/Engineering :: Physics
Classifier: License :: OSI Approved :: MIT License
Classifier: Programming Language :: Python :: 3.7
Requires-Python: >=3, <4
Requires-Dist: aerosandbox (>3.1.16)
